deeprai/__init__.py
deeprai/activation/__init__.py
deeprai/activation/leaky_relu.py
deeprai/activation/relu.py
deeprai/activation/sigmoid.py
deeprai/activation/softmax.py
deeprai/activation/tanh.py
deeprai/embedding/__init__.py
deeprai/embedding/positional_embeddings.py
deeprai/embedding/word_vectorize.py
deeprai/engine/__init__.py
deeprai/engine/base_layer.py
deeprai/engine/build_model.py
deeprai/engine/cython/__init__.py
deeprai/engine/cython/activation.cpython-311-x86_64-linux-gnu.so
deeprai/engine/cython/activation.pyx
deeprai/engine/cython/conv1d.pyx
deeprai/engine/cython/conv2d.pyx
deeprai/engine/cython/cython_optimizers.pyx
deeprai/engine/cython/dense_operations.cpython-311-x86_64-linux-gnu.so
deeprai/engine/cython/dense_operations.pyx
deeprai/engine/cython/dense_train_loop.cpython-311-x86_64-linux-gnu.so
deeprai/engine/cython/dense_train_loop.pyx
deeprai/engine/cython/knn.cpython-311-x86_64-linux-gnu.so
deeprai/engine/cython/knn.pyx
deeprai/engine/cython/knn_distance.cpython-311-x86_64-linux-gnu.so
deeprai/engine/cython/knn_distance.pyx
deeprai/engine/cython/loss.cpython-311-x86_64-linux-gnu.so
deeprai/engine/cython/loss.pyx
deeprai/engine/cython/optimizer_utils.pyx
deeprai/engine/cython/optimizers.cpython-311-x86_64-linux-gnu.so
deeprai/engine/cython/optimizers.pyx
deeprai/engine/cython/pool1d.pyx
deeprai/engine/cython/pool2d.pyx
deeprai/engine/cython/positional_embedding.cpython-311-x86_64-linux-gnu.so
deeprai/engine/cython/positional_embedding.pyx
deeprai/engine/cython/regression.cpython-311-x86_64-linux-gnu.so
deeprai/engine/cython/regression.pyx
deeprai/engine/cython/embeddings/positional_embedding.cpython-311-x86_64-linux-gnu.so
deeprai/loss/__init__.py
deeprai/loss/categorical_cross_entropy.py
deeprai/loss/mean_absolute_error.py
deeprai/loss/mean_square_error.py
deeprai/models/__init__.py
deeprai/models/KNN/KNN.py
deeprai/models/KNN/__init__.py
deeprai/models/convolutional/__init__.py
deeprai/models/convolutional/convolutional.py
DeeprAI-1.0.4.dist-info/LICENSE
DeeprAI-1.0.4.dist-info/METADATA
DeeprAI-1.0.4.dist-info/WHEEL
DeeprAI-1.0.4.dist-info/top_level.txt
DeeprAI-1.0.4.dist-info/RECORD
