Metadata-Version: 2.1
Name: DeeprAI
Version: 1.0.4
Summary: A easy to use and beginner friendly neural network tool box that anyone can pick up and explorer machine learning! 
Home-page: https://github.com/Deepr-ai/Deepr-ai
Author: Kieran Carter
Classifier: Programming Language :: Python :: 3
Classifier: Programming Language :: Cython
Classifier: License :: OSI Approved :: Apache Software License
Classifier: Operating System :: OS Independent
License-File: LICENSE
Requires-Dist: alive-progress
Requires-Dist: colorama
Requires-Dist: cryptography
Requires-Dist: cython
Requires-Dist: matplotlib
Requires-Dist: numpy
Requires-Dist: pyntree
